{
   "title": "Pi-Sat GPIO Demo initialization file",
   "description": [ "Define runtime configurations",
                    "GPIO Pin is the GPIO definition and not the physical pin number"]
   "config": {
      
      "APP_CFE_NAME": "SCSIM",
      "APP_PERF_ID":  128,
      
      "CHILD_NAME":       "GPIO_DEMO_CHILD",
      "CHILD_PERF_ID":    44,
      "CHILD_STACK_SIZE": 16384,
      "CHILD_PRIORITY":   80,

      "CMD_PIPE_NAME":  "GPIO_DEMO_CMD",
      "CMD_PIPE_DEPTH": 10,

      "CMD_MID"    : 8032,
      "SEND_HK_MID": 6594,
      "HK_TLM_MID" : 3936,
      
      "CTRL_OUT_PIN" :   18,
      "CTRL_ON_TIME" : 3000,
      "CTRL_OFF_TIME": 6000
  }
}
